{
  "moves": [
    {
      "learn_type": "tutor",
      "level": 0,
      "id": 343
    },
    {
      "learn_type": "tutor",
      "level": 0,
      "id": 304
    },
    {
      "learn_type": "machine",
      "level": 0,
      "id": 526
    },
    {
      "learn_type": "level up",
      "level": 25,
      "id": 516
    },
    {
      "learn_type": "machine",
      "level": 0,
      "id": 510
    },
    {
      "learn_type": "egg move",
      "level": 0,
      "id": 500
    },
    {
      "learn_type": "machine",
      "level": 0,
      "id": 497
    },
    {
      "learn_type": "machine",
      "level": 0,
      "id": 496
    },
    {
      "learn_type": "level up",
      "level": 53,
      "id": 495
    },
    {
      "learn_type": "machine",
      "level": 0,
      "id": 477
    },
    {
      "learn_type": "machine",
      "level": 0,
      "id": 473
    },
    {
      "learn_type": "egg move",
      "level": 0,
      "id": 234
    },
    {
      "learn_type": "egg move",
      "level": 0,
      "id": 326
    },
    {
      "learn_type": "tutor",
      "level": 0,
      "id": 277
    },
    {
      "learn_type": "tutor",
      "level": 0,
      "id": 215
    },
    {
      "learn_type": "tutor",
      "level": 0,
      "id": 428
    },
    {
      "learn_type": "tutor",
      "level": 0,
      "id": 324
    },
    {
      "learn_type": "tutor",
      "level": 0,
      "id": 283
    },
    {
      "learn_type": "tutor",
      "level": 0,
      "id": 271
    },
    {
      "learn_type": "tutor",
      "level": 0,
      "id": 253
    },
    {
      "learn_type": "machine",
      "level": 0,
      "id": 447
    },
    {
      "learn_type": "machine",
      "level": 0,
      "id": 445
    },
    {
      "learn_type": "egg move",
      "level": 0,
      "id": 417
    },
    {
      "learn_type": "level up",
      "level": 51,
      "id": 387
    },
    {
      "learn_type": "egg move",
      "level": 0,
      "id": 381
    },
    {
      "learn_type": "egg move",
      "level": 0,
      "id": 375
    },
    {
      "learn_type": "machine",
      "level": 0,
      "id": 374
    },
    {
      "learn_type": "machine",
      "level": 0,
      "id": 363
    },
    {
      "learn_type": "level up",
      "level": 21,
      "id": 246
    },
    {
      "learn_type": "level up",
      "level": 41,
      "id": 226
    },
    {
      "learn_type": "tutor",
      "level": 0,
      "id": 135
    },
    {
      "learn_type": "tutor",
      "level": 0,
      "id": 102
    },
    {
      "learn_type": "tutor",
      "level": 0,
      "id": 86
    },
    {
      "learn_type": "tutor",
      "level": 0,
      "id": 69
    },
    {
      "learn_type": "tutor",
      "level": 0,
      "id": 68
    },
    {
      "learn_type": "tutor",
      "level": 0,
      "id": 34
    },
    {
      "learn_type": "tutor",
      "level": 0,
      "id": 25
    },
    {
      "learn_type": "tutor",
      "level": 0,
      "id": 5
    },
    {
      "learn_type": "machine",
      "level": 0,
      "id": 352
    },
    {
      "learn_type": "machine",
      "level": 0,
      "id": 351
    },
    {
      "learn_type": "machine",
      "level": 0,
      "id": 290
    },
    {
      "learn_type": "level up",
      "level": 16,
      "id": 281
    },
    {
      "learn_type": "level up",
      "level": 31,
      "id": 273
    },
    {
      "learn_type": "level up",
      "level": 26,
      "id": 266
    },
    {
      "learn_type": "machine",
      "level": 0,
      "id": 263
    },
    {
      "learn_type": "egg move",
      "level": 0,
      "id": 164
    },
    {
      "learn_type": "machine",
      "level": 0,
      "id": 115
    },
    {
      "learn_type": "machine",
      "level": 0,
      "id": 113
    },
    {
      "learn_type": "tutor",
      "level": 0,
      "id": 53
    },
    {
      "learn_type": "machine",
      "level": 0,
      "id": 249
    },
    {
      "learn_type": "egg move",
      "level": 0,
      "id": 248
    },
    {
      "learn_type": "machine",
      "level": 0,
      "id": 247
    },
    {
      "learn_type": "machine",
      "level": 0,
      "id": 244
    },
    {
      "learn_type": "machine",
      "level": 0,
      "id": 241
    },
    {
      "learn_type": "machine",
      "level": 0,
      "id": 240
    },
    {
      "learn_type": "machine",
      "level": 0,
      "id": 237
    },
    {
      "learn_type": "level up",
      "level": 25,
      "id": 227
    },
    {
      "learn_type": "level up",
      "level": 31,
      "id": 219
    },
    {
      "learn_type": "machine",
      "level": 0,
      "id": 218
    },
    {
      "learn_type": "egg move",
      "level": 0,
      "id": 217
    },
    {
      "learn_type": "machine",
      "level": 0,
      "id": 216
    },
    {
      "learn_type": "machine",
      "level": 0,
      "id": 214
    },
    {
      "learn_type": "machine",
      "level": 0,
      "id": 213
    },
    {
      "learn_type": "machine",
      "level": 0,
      "id": 207
    },
    {
      "learn_type": "machine",
      "level": 0,
      "id": 205
    },
    {
      "learn_type": "level up",
      "level": 1,
      "id": 204
    },
    {
      "learn_type": "machine",
      "level": 0,
      "id": 203
    },
    {
      "learn_type": "machine",
      "level": 0,
      "id": 197
    },
    {
      "learn_type": "egg move",
      "level": 0,
      "id": 193
    },
    {
      "learn_type": "machine",
      "level": 0,
      "id": 192
    },
    {
      "learn_type": "machine",
      "level": 0,
      "id": 189
    },
    {
      "learn_type": "level up",
      "level": 18,
      "id": 186
    },
    {
      "learn_type": "machine",
      "level": 0,
      "id": 182
    },
    {
      "learn_type": "machine",
      "level": 0,
      "id": 174
    },
    {
      "learn_type": "machine",
      "level": 0,
      "id": 173
    },
    {
      "learn_type": "machine",
      "level": 0,
      "id": 156
    },
    {
      "learn_type": "machine",
      "level": 0,
      "id": 148
    },
    {
      "learn_type": "machine",
      "level": 0,
      "id": 138
    },
    {
      "learn_type": "machine",
      "level": 0,
      "id": 129
    },
    {
      "learn_type": "machine",
      "level": 0,
      "id": 126
    },
    {
      "learn_type": "egg move",
      "level": 0,
      "id": 119
    },
    {
      "learn_type": "level up",
      "level": 7,
      "id": 118
    },
    {
      "learn_type": "machine",
      "level": 0,
      "id": 111
    },
    {
      "learn_type": "machine",
      "level": 0,
      "id": 104
    },
    {
      "learn_type": "machine",
      "level": 0,
      "id": 94
    },
    {
      "learn_type": "machine",
      "level": 0,
      "id": 92
    },
    {
      "learn_type": "machine",
      "level": 0,
      "id": 76
    },
    {
      "learn_type": "egg move",
      "level": 0,
      "id": 64
    },
    {
      "learn_type": "level up",
      "level": 1,
      "id": 45
    },
    {
      "learn_type": "level up",
      "level": 38,
      "id": 38
    },
    {
      "learn_type": "machine",
      "level": 0,
      "id": 29
    }
  ],
  "_id": "00175",
  "_rev": "1-70200708a1aaa1851ef6b6901c9a849b"
}